django_filechest/__init__.py
django_filechest/__main__.py
django_filechest/asgi.py
django_filechest/settings.py
django_filechest/settings_adhoc.py
django_filechest/staticroot/admin/css/autocomplete.css
django_filechest/staticroot/admin/css/base.css
django_filechest/staticroot/admin/css/changelists.css
django_filechest/staticroot/admin/css/dark_mode.css
django_filechest/staticroot/admin/css/dashboard.css
django_filechest/staticroot/admin/css/forms.css
django_filechest/staticroot/admin/css/login.css
django_filechest/staticroot/admin/css/nav_sidebar.css
django_filechest/staticroot/admin/css/responsive.css
django_filechest/staticroot/admin/css/responsive_rtl.css
django_filechest/staticroot/admin/css/rtl.css
django_filechest/staticroot/admin/css/unusable_password_field.css
django_filechest/staticroot/admin/css/vendor/select2/LICENSE-SELECT2.md
django_filechest/staticroot/admin/css/vendor/select2/select2.css
django_filechest/staticroot/admin/css/vendor/select2/select2.min.css
django_filechest/staticroot/admin/css/widgets.css
django_filechest/staticroot/admin/img/README.md
django_filechest/staticroot/admin/img/calendar-icons.svg
django_filechest/staticroot/admin/img/icon-addlink.svg
django_filechest/staticroot/admin/img/icon-alert-dark.svg
django_filechest/staticroot/admin/img/icon-alert.svg
django_filechest/staticroot/admin/img/icon-calendar.svg
django_filechest/staticroot/admin/img/icon-changelink.svg
django_filechest/staticroot/admin/img/icon-clock.svg
django_filechest/staticroot/admin/img/icon-debug-dark.svg
django_filechest/staticroot/admin/img/icon-debug.svg
django_filechest/staticroot/admin/img/icon-deletelink.svg
django_filechest/staticroot/admin/img/icon-hidelink.svg
django_filechest/staticroot/admin/img/icon-info-dark.svg
django_filechest/staticroot/admin/img/icon-info.svg
django_filechest/staticroot/admin/img/icon-no-dark.svg
django_filechest/staticroot/admin/img/icon-no.svg
django_filechest/staticroot/admin/img/icon-unknown-alt.svg
filechest-0.6.0.dist-info/WHEEL
filechest-0.6.0.dist-info/entry_points.txt
filechest-0.6.0.dist-info/METADATA
filechest-0.6.0.dist-info/RECORD
