Metadata-Version: 2.3
Name: filechest
Version: 0.6.0
Summary: A simple file manager for Django with S3 support
Classifier: Development Status :: 3 - Alpha
Classifier: Framework :: Django
Classifier: Framework :: Django :: 5.2
Classifier: License :: OSI Approved :: MIT License
Classifier: Programming Language :: Python :: 3
Classifier: Programming Language :: Python :: 3.10
Classifier: Programming Language :: Python :: 3.11
Classifier: Programming Language :: Python :: 3.12
Classifier: Programming Language :: Python :: 3.13
Classifier: Programming Language :: Python :: 3.14
Classifier: Intended Audience :: Developers
Classifier: Topic :: Internet :: WWW/HTTP :: Dynamic Content :: Content Management System
Requires-Dist: django>=5.2.0
Requires-Dist: boto3>=1.35.0
Requires-Dist: whitenoise>=6.11.0
Requires-Dist: pywebview[gtk]>=6.1 ; extra == 'gtk'
Requires-Dist: pywebview>=6.1 ; extra == 'gui'
Requires-Dist: pywebview[qt]>=6.1 ; extra == 'qt'
Requires-Python: >=3.10
Project-URL: Homepage, https://github.com/atsuoishimoto/filechest
Project-URL: Repository, https://github.com/atsuoishimoto/filechest
Project-URL: Issues, https://github.com/atsuoishimoto/filechest/issues
Provides-Extra: gtk
Provides-Extra: gui
Provides-Extra: qt
